aiconf/__init__.py
aiconf/aiconf.py
aiconf/construct.py
aiconf/exceptions.py
AIConf-1.1.7.dist-info/METADATA
AIConf-1.1.7.dist-info/WHEEL
AIConf-1.1.7.dist-info/top_level.txt
AIConf-1.1.7.dist-info/RECORD
