Metadata-Version: 2.1
Name: AIConf
Version: 1.1.7
Summary: Config reader and Factory method provider to create instances from given configs
Home-page: http://github.com/ai-systems/AIConf
Author: AI Systems, University of Manchester
Author-email: viktor.schlegel@manchester.ac.uk
License: MIT
Platform: UNKNOWN
Requires-Dist: pyhocon
Requires-Dist: overrides
